docp/__init__.py
docp/_version.py
docp-0.0.0.dev1.dist-info/LICENSE
docp-0.0.0.dev1.dist-info/METADATA
docp-0.0.0.dev1.dist-info/WHEEL
docp-0.0.0.dev1.dist-info/top_level.txt
docp-0.0.0.dev1.dist-info/RECORD
